pretty_logic/__init__.py
pretty_logic/pretty_logic.py
pretty_logic-1.0.1.dist-info/LICENSE
pretty_logic-1.0.1.dist-info/METADATA
pretty_logic-1.0.1.dist-info/WHEEL
pretty_logic-1.0.1.dist-info/top_level.txt
pretty_logic-1.0.1.dist-info/RECORD
