Metadata-Version: 2.1
Name: pretty-logic
Version: 1.0.1
Summary: A pretty logic library
Home-page: https://github.com/aqeelat/pretty-logic.git
Author: Abdullah Alaqeel
Author-email: abdullah.t.aqeel@gmail.com
License: MIT
Platform: UNKNOWN
Classifier: Programming Language :: Python :: 3
Classifier: License :: OSI Approved :: MIT License
Classifier: Operating System :: OS Independent
